social_validator/__init__.py
social_validator/exceptions.py
social_validator/shared.py
social_validator/telegram.py
social_validator/twitch.py
social_validator/youtube.py
social_validator-0.3.1.dist-info/METADATA
social_validator-0.3.1.dist-info/WHEEL
social_validator-0.3.1.dist-info/licenses/LICENSE
social_validator-0.3.1.dist-info/RECORD
